LICENSE.txt
MANIFEST.in
README.md
setup.py
ellipticcurve/__init__.py
ellipticcurve/curve.py
ellipticcurve/ecdsa.py
ellipticcurve/math.py
ellipticcurve/point.py
ellipticcurve/privateKey.py
ellipticcurve/publicKey.py
ellipticcurve/signature.py
ellipticcurve/utils/__init__.py
ellipticcurve/utils/base.py
ellipticcurve/utils/binary.py
ellipticcurve/utils/compatibility.py
ellipticcurve/utils/der.py
ellipticcurve/utils/file.py
ellipticcurve/utils/integer.py
starkbank_ecdsa.egg-info/PKG-INFO
starkbank_ecdsa.egg-info/SOURCES.txt
starkbank_ecdsa.egg-info/dependency_links.txt
starkbank_ecdsa.egg-info/top_level.txt
test/__init__.py
test/testEcdsa.py
test/testOpenSSL.py
test/testPrivateKey.py
test/testPublicKey.py
test/testSignature.py