Metadata-Version: 2.1
Name: starkbank-ecdsa
Version: 0.1.6
Summary: A lightweight and fast pure python ECDSA library
Home-page: https://github.com/starkbank/ecdsa-python.git
Author: Stark Bank
Author-email: developers@starkbank.com
License: MIT License
Keywords: ecdsa,elliptic curve,elliptic,curve,stark bank,starkbank,cryptograph
Platform: UNKNOWN
